firebase_sdk/__init__.py
firebase_sdk/py.typed
firebase_sdk-0.0.3.dist-info/licenses/LICENSE.md
firebase_sdk-0.0.3.dist-info/WHEEL
firebase_sdk-0.0.3.dist-info/METADATA
firebase_sdk-0.0.3.dist-info/RECORD
