Metadata-Version: 2.4
Name: firebase-sdk
Version: 0.0.3
Summary: Pythonic Firebase Admin Python SDK
Keywords: firebase
Author: AlphaKR93
Author-email: AlphaKR93 <dev@alpha93.kr>
License-Expression: MIT
License-File: LICENSE.md
Classifier: Development Status :: 1 - Planning
Classifier: License :: OSI Approved :: MIT License
Classifier: Typing :: Typed
Classifier: Topic :: Software Development :: Libraries
Classifier: Topic :: Software Development :: Libraries :: Python Modules
Classifier: Programming Language :: Python
Classifier: Programming Language :: Python :: 3
Classifier: Programming Language :: Python :: 3 :: Only
Classifier: Programming Language :: Python :: 3.10
Classifier: Programming Language :: Python :: 3.11
Classifier: Programming Language :: Python :: 3.12
Classifier: Programming Language :: Python :: 3.13
Classifier: Programming Language :: Python :: 3.14
Classifier: Programming Language :: Python :: 3.15
Requires-Python: >=3.10
Project-URL: Changelog, https://github.com/AlphaKR93/workspace/blob/main/python/firebase-sdk/CHANGELOG.md
Project-URL: Issues, https://github.com/AlphaKR93/workspace/issues
Project-URL: Source, https://github.com/AlphaKR93/workspace/tree/main/python/firebase-sdk
Project-URL: Sponsor, https://github.com/sponsors/AlphaKR93
